chatos/__init__.py
chatos/__main__.py
chatos/chat_serial.py
chatos-0.0.3.dist-info/LICENSE
chatos-0.0.3.dist-info/METADATA
chatos-0.0.3.dist-info/WHEEL
chatos-0.0.3.dist-info/top_level.txt
chatos-0.0.3.dist-info/RECORD
