Metadata-Version: 2.1
Name: chatos
Version: 0.0.3
Summary: REV 0.0.3 Stablish a communication between the computer and the microcontroller CH552 using the serial port.
Author: Master
Author-email: name@email.com
License: GPL-3.0 License
License-File: LICENSE
Requires-Dist: tk
Requires-Dist: pyusb
Requires-Dist: pyserial
